Live2dTK/__init__.py
live2dtk-1.0.1.dist-info/METADATA
live2dtk-1.0.1.dist-info/WHEEL
live2dtk-1.0.1.dist-info/top_level.txt
live2dtk-1.0.1.dist-info/RECORD
