Metadata-Version: 2.2
Name: Live2dTk
Version: 1.0.1
Summary: live2d performance on tkinter based on live2d_py
Home-page: https://github.com/Ashisheng2005/Live2dTK
Author: HUZHAOJUN
Author-email: 3237495209@qq.com
Project-URL: Bug Reports, https://github.com/Ashisheng2005/Live2dTK/issues
Project-URL: Source, https://github.com/Ashisheng2005/Live2dTK
Keywords: tkinter,widget,live2d,TK,opengl
Classifier: Development Status :: 3 - Alpha
Classifier: Intended Audience :: Developers
Classifier: Topic :: Software Development :: Build Tools
Classifier: License :: OSI Approved :: MIT License
Classifier: Programming Language :: Python :: 3
Classifier: Programming Language :: Python :: 3.7
Classifier: Programming Language :: Python :: 3.8
Classifier: Programming Language :: Python :: 3.9
Classifier: Programming Language :: Python :: 3.10
Classifier: Programming Language :: Python :: 3 :: Only
Requires-Python: >=3.12, <4
Requires-Dist: live2d-py>=0.4.2
Requires-Dist: PyOpenGL
Requires-Dist: pyopengltk>=0.0.4
Requires-Dist: pyautogui
Dynamic: author
Dynamic: author-email
Dynamic: classifier
Dynamic: description
Dynamic: description-content-type
Dynamic: home-page
Dynamic: keywords
Dynamic: project-url
Dynamic: requires-dist
Dynamic: requires-python
Dynamic: summary
